README.md
setup.cfg
setup.py
rankhub/__init__.py
rankhub/rankhub.py
rankhub/ranking.py
rankhub.egg-info/PKG-INFO
rankhub.egg-info/SOURCES.txt
rankhub.egg-info/dependency_links.txt
rankhub.egg-info/requires.txt
rankhub.egg-info/top_level.txt
tests/__init__.py
tests/test_rankhub.py