Metadata-Version: 2.1
Name: rankhub
Version: 0.0.1
Summary: rankhub - is a Python package to generate GitHub users rankings
Home-page: https://github.com/alvarob96/rankhub
Author: Alvaro Bartolome
Author-email: alvarob96@usal.es
License: MIT License
Download-URL: https://github.com/alvarob96/rankhub/archive/0.0.1.tar.gz
Project-URL: Bug Reports, https://github.com/alvarob96/rankhub/issues
Project-URL: Source, https://github.com/alvarob96/rankhub
Keywords: github-api,github-ranking,salamanca-github
Platform: UNKNOWN
Classifier: Development Status :: 3 - Alpha
Classifier: Programming Language :: Python :: 3 :: Only
Classifier: Programming Language :: Python :: 3.5
Classifier: Programming Language :: Python :: 3.6
Classifier: Programming Language :: Python :: 3.7
Classifier: License :: OSI Approved :: MIT License
Classifier: Intended Audience :: Developers
Classifier: Topic :: Scientific/Engineering :: Information Analysis
Requires-Python: >=3
